{"_id": "5166c35a34309d2f05a8bd65", "categories": {"audience": [{"fullname": "End Users/Desktop", "fullpath": "Intended Audience :: by End-User Class :: End Users/Desktop", "id": 2, "shortname": "endusers"}], "database": [], "developmentstatus": [{"fullname": "1 - Planning", "fullpath": "Development Status :: 1 - Planning", "id": 7, "shortname": "planning"}], "environment": [{"fullname": "Java Swing", "fullpath": "User Interface :: Graphical :: Java Swing", "id": 471, "shortname": "ui_swing"}], "language": [{"fullname": "Java", "fullpath": "Programming Language :: Java", "id": 198, "shortname": "java"}], "license": [{"fullname": "GNU General Public License version 2.0 (GPLv2)", "fullpath": "License :: OSI-Approved Open Source :: GNU General Public License version 2.0 (GPLv2)", "id": 15, "shortname": "gpl"}], "os": [], "topic": [{"fullname": "Board Games", "fullpath": "Topic :: Games/Entertainment :: Board Games", "id": 287, "shortname": "boardgames"}], "translation": [{"fullname": "English", "fullpath": "Translations :: English", "id": 275, "shortname": "english"}, {"fullname": "Chinese (Simplified)", "fullpath": "Translations :: Chinese (Simplified)", "id": 382, "shortname": "chinesesimplified"}]}, "creation_date": "2010-05-28", "developers": [{"name": "liu yongjun", "url": "http://sourceforge.net/u/ssikkiss/", "username": "ssikkiss"}], "external_homepage": "http://sokotool.sourceforge.net", "icon_url": null, "labels": [], "moved_to_url": "", "name": "SokoTool", "preferred_support_tool": "", "preferred_support_url": "", "private": false, "screenshots": [], "short_description": "SokoTool is a Java program for solve or edit the game of Sokoban.It is cool,and I will Continues to try hard to cause it to be more intelligent .", "shortname": "sokotool", "socialnetworks": [], "status": "active", "summary": "", "tools": [{"label": "Summary", "mount_point": "summary", "name": "summary", "sourceforge_group_id": 325585}, {"label": "Support", "mount_point": "support", "name": "support"}, {"label": "Reviews", "mount_point": "reviews", "name": "reviews"}, {"label": "Files", "mount_point": "files", "name": "files"}, {"label": "Wiki", "mount_point": "wiki", "name": "wiki"}, {"label": "Activity", "mount_point": "activity", "name": "activity"}], "url": "http://sourceforge.net/p/sokotool/", "video_url": ""}
