{"status": "active", "external_homepage": "http://fs-inspect.googlecode.com", "developers": [{"url": "http://sourceforge.net/u/taibal/", "username": "taibal", "name": "E.H."}], "screenshots": [{"url": "http://sourceforge.net/p/fs-inspect/screenshot/326273.jpg", "caption": "FS-Inspect 1.7", "thumbnail_url": "http://sourceforge.net/p/fs-inspect/screenshot/326273.jpg/thumb"}, {"url": "http://sourceforge.net/p/fs-inspect/screenshot/328543.jpg", "caption": "", "thumbnail_url": "http://sourceforge.net/p/fs-inspect/screenshot/328543.jpg/thumb"}, {"url": "http://sourceforge.net/p/fs-inspect/screenshot/328545.jpg", "caption": "", "thumbnail_url": "http://sourceforge.net/p/fs-inspect/screenshot/328545.jpg/thumb"}], "name": "FS-Inspect", "preferred_support_tool": "", "preferred_support_url": "", "icon_url": "http://sourceforge.net/p/fs-inspect/icon", "labels": [], "video_url": "", "private": false, "creation_date": "2008-07-21", "url": "http://sourceforge.net/p/fs-inspect/", "socialnetworks": [], "short_description": "FS-Inspect is an easy to use tool designed to give you an overview about your files and directories (Disk Usage).\r\n\r\nOn start up, it reads recursively the inspected directory and presents the content in two useful views:\r\n\r\n* The folder view, shows the directory tree, sub-folders are sorted by size.\r\n* The type view, shows all file types found, sorted by the total size. \r\n\r\nIn the post scan, the utility start searching for duplicates. All duplicates are listed in the file view, colored depending on their MD5-checksum.\r\n\r\nIt is possible to configure the duplicate search in the settings. To optimize the duplicate search, hashes are stored in a database. If a directory is inspected many a time, there is no need to compute the performance-expensive check-sum again. ", "moved_to_url": "", "shortname": "fs-inspect", "_id": "513bc19734309d2e91e8c145", "tools": [{"sourceforge_group_id": 234666, "mount_point": "summary", "name": "summary", "label": "Summary"}, {"mount_point": "support", "name": "support", "label": "Support"}, {"mount_point": "reviews", "name": "reviews", "label": "Reviews"}, {"mount_point": "wiki", "name": "wiki", "label": "Wiki"}, {"mount_point": "files", "name": "files", "label": "Files"}, {"mount_point": "bugs", "name": "tickets", "label": "Bugs"}, {"mount_point": "feature-requests", "name": "tickets", "label": "Feature Requests"}, {"mount_point": "donate", "name": "link", "label": "Donate"}, {"mount_point": "svnexternalurl", "name": "link", "label": "Browse SVN"}, {"mount_point": "activity", "name": "activity", "label": "Activity"}], "summary": "", "categories": {"developmentstatus": [{"fullpath": "Development Status :: 5 - Production/Stable", "shortname": "production", "fullname": "5 - Production/Stable", "id": 11}], "topic": [{"fullpath": "Topic :: System :: Storage", "shortname": "storage", "fullname": "Storage", "id": 638}, {"fullpath": "Topic :: System :: Systems Administration", "shortname": "sysadministration", "fullname": "Systems Administration", "id": 253}, {"fullpath": "Topic :: System :: Filesystems", "shortname": "filesystems", "fullname": "Filesystems", "id": 142}], "language": [{"fullpath": "Programming Language :: C++", "shortname": "cpp", "fullname": "C++", "id": 165}], "license": [{"fullpath": "License :: OSI-Approved Open Source :: Artistic License 2.0", "shortname": "artisticv2", "fullname": "Artistic License 2.0", "id": 677}], "database": [{"fullpath": "Database Environment :: Database API :: SQL-based", "shortname": "db_api_sql", "fullname": "SQL-based", "id": 508}], "environment": [{"fullpath": "User Interface :: Graphical :: Win32 (MS Windows)", "shortname": "win32", "fullname": "Win32 (MS Windows)", "id": 230}, {"fullpath": "User Interface :: Graphical :: Windows Aero", "shortname": "winaero", "fullname": "Windows Aero", "id": 763}], "audience": [{"fullpath": "Intended Audience :: by End-User Class :: Advanced End Users", "shortname": "enduser_advanced", "fullname": "Advanced End Users", "id": 536}, {"fullpath": "Intended Audience :: by End-User Class :: System Administrators", "shortname": "sysadmins", "fullname": "System Administrators", "id": 4}, {"fullpath": "Intended Audience :: by End-User Class :: Developers", "shortname": "developers", "fullname": "Developers", "id": 3}, {"fullpath": "Intended Audience :: by End-User Class :: End Users/Desktop", "shortname": "endusers", "fullname": "End Users/Desktop", "id": 2}], "translation": [], "os": [{"fullpath": "Operating System :: Modern (Vendor-Supported) Desktop Operating Systems :: WinXP", "shortname": "mswin_xp", "fullname": "WinXP", "id": 419}, {"fullpath": "Operating System :: Modern (Vendor-Supported) Desktop Operating Systems :: Vista", "shortname": "vista", "fullname": "Vista", "id": 657}, {"fullpath": "Operating System :: Modern (Vendor-Supported) Desktop Operating Systems :: Windows 7", "shortname": "win7", "fullname": "Windows 7", "id": 851}]}}
