{"status": "active", "external_homepage": "", "developers": [{"url": "http://sourceforge.net/u/tombetoile/", "username": "tombetoile", "name": "Delerin Anthony"}], "screenshots": [], "name": "Digigotchi", "preferred_support_tool": "wiki", "preferred_support_url": "", "icon_url": null, "labels": [], "video_url": "", "private": false, "creation_date": "2012-10-08", "url": "http://sourceforge.net/p/digigotchi/", "socialnetworks": [], "short_description": "Page ", "moved_to_url": "", "shortname": "digigotchi", "_id": "5072c9831be1ce27f71c8cb1", "tools": [{"mount_point": "wiki", "name": "wiki", "label": "Wiki"}, {"mount_point": "downloads", "name": "files", "label": "Files"}, {"mount_point": "tickets", "name": "tickets", "label": "Tickets"}, {"mount_point": "blog", "name": "blog", "label": "Blog"}, {"mount_point": "code", "name": "svn", "label": "Code"}, {"sourceforge_group_id": 1003004, "mount_point": "summary", "name": "summary", "label": "Summary"}, {"mount_point": "reviews", "name": "reviews", "label": "Reviews"}, {"mount_point": "support", "name": "support", "label": "Support"}], "summary": "Jeu de gestion en temps r\u00e9el d'une petite entit\u00e9", "categories": {"developmentstatus": [], "topic": [], "language": [], "license": [], "database": [], "environment": [], "audience": [], "translation": [], "os": []}}
