{"status": "active", "external_homepage": "http://digitalmap.sourceforge.net", "developers": [{"url": "http://sourceforge.net/u/szulist/", "username": "szulist", "name": "Mariusz Szulist"}], "screenshots": [], "name": "DigitalMap", "preferred_support_tool": "", "preferred_support_url": "", "icon_url": null, "labels": [], "video_url": "", "private": false, "creation_date": "2011-02-08", "url": "http://sourceforge.net/p/digitalmap/", "socialnetworks": [], "short_description": "Mgr digital map for mobile devices", "moved_to_url": "", "shortname": "digitalmap", "_id": "5179769fe88f3d0ab9c4d911", "tools": [{"sourceforge_group_id": 405506, "mount_point": "summary", "name": "summary", "label": "Summary"}, {"mount_point": "support", "name": "support", "label": "Support"}, {"mount_point": "reviews", "name": "reviews", "label": "Reviews"}, {"mount_point": "wiki", "name": "wiki", "label": "Wiki"}, {"mount_point": "files", "name": "files", "label": "Files"}, {"mount_point": "code", "name": "svn", "label": "Code"}], "summary": "", "categories": {"developmentstatus": [], "topic": [], "language": [], "license": [], "database": [], "environment": [], "audience": [], "translation": [], "os": []}}
