{"status": "active", "external_homepage": "", "developers": [{"url": "http://sourceforge.net/u/teixeluis/", "username": "teixeluis", "name": "Luis Teixeira"}], "screenshots": [{"url": "http://sourceforge.net/p/digidosemeter/screenshot/DSCF0245.JPG", "caption": "", "thumbnail_url": "http://sourceforge.net/p/digidosemeter/screenshot/DSCF0245.JPG/thumb"}], "name": "DigiDosimeter", "preferred_support_tool": "", "preferred_support_url": "", "icon_url": null, "labels": ["Digital Radiation Dosimeter"], "video_url": "", "private": false, "creation_date": "2012-03-11", "url": "http://sourceforge.net/p/digidosemeter/", "socialnetworks": [], "short_description": "This project consists of a high energy radiation measurement tool. It can be distinguished from other projects due to its modular nature. Detector and User Interface modules are separate and communicate via a I2C bus. This enables the UI component to be used together with a variety of different types of detectors, as long as these implement the same set of commands for accessing the event counter, dose measurement (if available) or other data the detector might provide. This project readily specifies the hardware and firmware for a user interface module, and a Geiger Muller based detector. The schematics and source code are therefore provided as public domain contributions of the author of this project.", "moved_to_url": "", "shortname": "digidosemeter", "_id": "4f5d0a2bb9363c69680005ed", "tools": [{"mount_point": "wiki", "name": "wiki", "label": "Wiki"}, {"mount_point": "downloads", "name": "files", "label": "Files"}, {"mount_point": "discussion", "name": "discussion", "label": "Discussion"}, {"mount_point": "code", "name": "svn", "label": "Code"}, {"mount_point": "tickets", "name": "tickets", "label": "Tickets"}, {"sourceforge_group_id": 720780, "mount_point": "summary", "name": "summary", "label": "Summary"}, {"mount_point": "reviews", "name": "reviews", "label": "Reviews"}, {"mount_point": "support", "name": "support", "label": "Support"}, {"mount_point": "activity", "name": "activity", "label": "Activity"}], "summary": "Versatile high energy radiation measurement tool ", "categories": {"developmentstatus": [{"fullpath": "Development Status :: 4 - Beta", "shortname": "beta", "fullname": "4 - Beta", "id": 10}], "topic": [{"fullpath": "Topic :: Scientific/Engineering :: Physics", "shortname": "physics", "fullname": "Physics", "id": 387}], "language": [{"fullpath": "Programming Language :: C", "shortname": "c", "fullname": "C", "id": 164}], "license": [{"fullpath": "License :: Public Domain", "shortname": "publicdomain", "fullname": "Public Domain", "id": 197}], "database": [], "environment": [], "audience": [{"fullpath": "Intended Audience :: by Industry or Sector :: Science/Research", "shortname": "scienceresearch", "fullname": "Science/Research", "id": 367}], "translation": [], "os": []}}
