{"_id": "516c4d592718467af2b1b46b", "categories": {"audience": [{"fullname": "Developers", "fullpath": "Intended Audience :: by End-User Class :: Developers", "id": 3, "shortname": "developers"}, {"fullname": "End Users/Desktop", "fullpath": "Intended Audience :: by End-User Class :: End Users/Desktop", "id": 2, "shortname": "endusers"}], "database": [], "developmentstatus": [{"fullname": "5 - Production/Stable", "fullpath": "Development Status :: 5 - Production/Stable", "id": 11, "shortname": "production"}], "environment": [{"fullname": "X Window System (X11)", "fullpath": "User Interface :: Graphical :: X Window System (X11)", "id": 229, "shortname": "x11"}], "language": [{"fullname": "C++", "fullpath": "Programming Language :: C++", "id": 165, "shortname": "cpp"}], "license": [{"fullname": "GNU General Public License version 2.0 (GPLv2)", "fullpath": "License :: OSI-Approved Open Source :: GNU General Public License version 2.0 (GPLv2)", "id": 15, "shortname": "gpl"}], "os": [{"fullname": "Solaris", "fullpath": "Operating System :: Modern (Vendor-Supported) Desktop Operating Systems :: Solaris", "id": 207, "shortname": "sun"}, {"fullname": "Linux", "fullpath": "Operating System :: Modern (Vendor-Supported) Desktop Operating Systems :: Linux", "id": 201, "shortname": "linux"}, {"fullname": "FreeBSD", "fullpath": "Operating System :: Modern (Vendor-Supported) Desktop Operating Systems :: FreeBSD", "id": 203, "shortname": "freebsd"}, {"fullname": "OS X", "fullpath": "Operating System :: Modern (Vendor-Supported) Desktop Operating Systems :: OS X", "id": 309, "shortname": "macosx"}, {"fullname": "All POSIX (Linux/BSD/UNIX-like OSes)", "fullpath": "Operating System :: Grouping and Descriptive Categories :: All POSIX (Linux/BSD/UNIX-like OSes)", "id": 200, "shortname": "posix"}, {"fullname": "All BSD Platforms (FreeBSD/NetBSD/OpenBSD/Apple Mac OS X)", "fullpath": "Operating System :: Grouping and Descriptive Categories :: All BSD Platforms (FreeBSD/NetBSD/OpenBSD/Apple Mac OS X)", "id": 202, "shortname": "bsd"}], "topic": [{"fullname": "Window Managers", "fullpath": "Topic :: Desktop Environment :: Window Managers", "id": 56, "shortname": "windowmanagers"}], "translation": [{"fullname": "English", "fullpath": "Translations :: English", "id": 275, "shortname": "english"}]}, "creation_date": "2003-06-18", "developers": [{"name": "Ben Wise", "url": "http://sourceforge.net/u/bwise837/", "username": "bwise837"}], "external_homepage": "http://miwm.sourceforge.net", "icon_url": null, "labels": [], "moved_to_url": "", "name": "miwm", "preferred_support_tool": "", "preferred_support_url": "", "private": false, "screenshots": [], "short_description": "MIWM is a minimalist window manager with virtual workspaces. MIWM is written in C++, for the X window system.", "shortname": "miwm", "socialnetworks": [], "status": "active", "summary": "", "tools": [{"label": "Summary", "mount_point": "summary", "name": "summary", "sourceforge_group_id": 83675}, {"label": "Support", "mount_point": "support", "name": "support"}, {"label": "Reviews", "mount_point": "reviews", "name": "reviews"}, {"label": "Files", "mount_point": "files", "name": "files"}, {"label": "Wiki", "mount_point": "wiki", "name": "wiki"}, {"label": "Bugs", "mount_point": "bugs", "name": "tickets"}, {"label": "Feature Requests", "mount_point": "feature-requests", "name": "tickets"}, {"label": "Donate", "mount_point": "donate", "name": "link"}, {"label": "Code", "mount_point": "code", "name": "cvs"}, {"label": "Mailing Lists", "mount_point": "mailman", "name": "mailman"}, {"label": "Activity", "mount_point": "activity", "name": "activity"}], "url": "http://sourceforge.net/p/miwm/", "video_url": ""}
