{"status": "active", "external_homepage": "http://syspeak.sourceforge.net", "developers": [{"url": "http://sourceforge.net/u/clydegoffe/", "username": "clydegoffe", "name": "Clyde Goffe"}, {"url": "http://sourceforge.net/u/jhlinder/", "username": "jhlinder", "name": "James H. Linder"}], "screenshots": [], "name": "System Peak", "preferred_support_tool": "", "preferred_support_url": "", "icon_url": null, "labels": [], "video_url": "", "private": false, "creation_date": "2007-10-04", "url": "http://sourceforge.net/p/syspeak/", "socialnetworks": [], "short_description": "An application that centralizes UNIX system status information from several machines into one web-accessible interface.  A daemon gathers system stats and reports them stats via HTTP to a server which presents the most recent stats via a web page.", "moved_to_url": "", "shortname": "syspeak", "_id": "514cbec134309d541b8a0c62", "tools": [{"sourceforge_group_id": 207150, "mount_point": "summary", "name": "summary", "label": "Summary"}, {"mount_point": "support", "name": "support", "label": "Support"}, {"mount_point": "reviews", "name": "reviews", "label": "Reviews"}, {"mount_point": "wiki", "name": "wiki", "label": "Wiki"}, {"mount_point": "files", "name": "files", "label": "Files"}, {"mount_point": "code", "name": "cvs", "label": "Code"}], "summary": "", "categories": {"developmentstatus": [{"fullpath": "Development Status :: 4 - Beta", "shortname": "beta", "fullname": "4 - Beta", "id": 10}], "topic": [{"fullpath": "Topic :: Internet :: WWW/HTTP :: Site Management", "shortname": "sitemanagement", "fullname": "Site Management", "id": 243}, {"fullpath": "Topic :: System :: Systems Administration", "shortname": "sysadministration", "fullname": "Systems Administration", "id": 253}, {"fullpath": "Topic :: System :: Logging", "shortname": "logging", "fullname": "Logging", "id": 148}], "language": [{"fullpath": "Programming Language :: Unix Shell", "shortname": "shell", "fullname": "Unix Shell", "id": 185}, {"fullpath": "Programming Language :: Perl", "shortname": "perl", "fullname": "Perl", "id": 176}, {"fullpath": "Programming Language :: JavaScript", "shortname": "JavaScript", "fullname": "JavaScript", "id": 280}], "license": [{"fullpath": "License :: OSI-Approved Open Source :: GNU General Public License version 2.0 (GPLv2)", "shortname": "gpl", "fullname": "GNU General Public License version 2.0 (GPLv2)", "id": 15}], "database": [{"fullpath": "Database Environment :: Database API :: Perl DBI/DBD", "shortname": "db_api_perldbi", "fullname": "Perl DBI/DBD", "id": 504}], "environment": [{"fullpath": "User Interface :: Web-based", "shortname": "web", "fullname": "Web-based", "id": 237}, {"fullpath": "User Interface :: Non-interactive (Daemon)", "shortname": "daemon", "fullname": "Non-interactive (Daemon)", "id": 238}], "audience": [{"fullpath": "Intended Audience :: by Industry or Sector :: Information Technology", "shortname": "informationtechnology", "fullname": "Information Technology", "id": 363}, {"fullpath": "Intended Audience :: by End-User Class :: System Administrators", "shortname": "sysadmins", "fullname": "System Administrators", "id": 4}, {"fullpath": "Intended Audience :: Other Audience", "shortname": "other", "fullname": "Other Audience", "id": 5}], "translation": [{"fullpath": "Translations :: English", "shortname": "english", "fullname": "English", "id": 275}], "os": [{"fullpath": "Operating System :: Grouping and Descriptive Categories :: All POSIX (Linux/BSD/UNIX-like OSes)", "shortname": "posix", "fullname": "All POSIX (Linux/BSD/UNIX-like OSes)", "id": 200}]}}
