{"_id": "50260a6ab9363c01eb2cda2a", "categories": {"audience": [], "database": [], "developmentstatus": [], "environment": [], "language": [], "license": [], "os": [], "topic": [], "translation": []}, "creation_date": "2012-08-11", "developers": [{"name": "bulkcell", "url": "http://sourceforge.net/u/bulkcell/", "username": "bulkcell"}], "external_homepage": "http://www.cellbulk.com/", "icon_url": null, "labels": [], "moved_to_url": "", "name": "Buy samsung mobiles", "preferred_support_tool": "_url", "preferred_support_url": "http://www.cellbulk.com/Mobiles/Samsung", "private": false, "screenshots": [], "short_description": "CellBulk Buy the best and latest smartphones samsung mobiles india,samsung smartphones,samsung mobile price in India,available with full specification,review, comparison and photos", "shortname": "buysamsungmobil", "socialnetworks": [], "status": "active", "summary": " phones available in India with full specifications, reviews, comparis", "tools": [{"label": "Files", "mount_point": "downloads", "name": "files"}, {"label": "Wiki", "mount_point": "wiki", "name": "wiki"}, {"label": "Code", "mount_point": "code", "name": "git"}, {"label": "Tickets", "mount_point": "tickets", "name": "tickets"}, {"label": "Discussion", "mount_point": "discussion", "name": "discussion"}, {"label": "Blog", "mount_point": "blog", "name": "blog"}, {"label": "Summary", "mount_point": "summary", "name": "summary", "sourceforge_group_id": 848550}, {"label": "Reviews", "mount_point": "reviews", "name": "reviews"}, {"label": "Support", "mount_point": "support", "name": "support"}, {"label": "Activity", "mount_point": "activity", "name": "activity"}], "url": "http://sourceforge.net/p/buysamsungmobil/", "video_url": ""}
