{"_id": "5178001be88f3d0ab9c1e3dd", "categories": {"audience": [], "database": [], "developmentstatus": [], "environment": [], "language": [], "license": [], "os": [], "topic": [], "translation": []}, "creation_date": "2010-05-13", "developers": [{"name": "Hailing Zhang", "url": "http://sourceforge.net/u/hlzhang/", "username": "hlzhang"}, {"name": "24850470 ", "url": "http://sourceforge.net/u/qq24850470/", "username": "qq24850470"}, {"name": "fred liao", "url": "http://sourceforge.net/u/liaof2/", "username": "liaof2"}], "external_homepage": "http://tzdata.sourceforge.net", "icon_url": null, "labels": [], "moved_to_url": "", "name": "data management", "preferred_support_tool": "", "preferred_support_url": "", "private": false, "screenshots": [], "short_description": "data management online", "shortname": "tzdata", "socialnetworks": [], "status": "active", "summary": "", "tools": [{"label": "Summary", "mount_point": "summary", "name": "summary", "sourceforge_group_id": 322339}, {"label": "Support", "mount_point": "support", "name": "support"}, {"label": "Reviews", "mount_point": "reviews", "name": "reviews"}, {"label": "Files", "mount_point": "files", "name": "files"}, {"label": "Wiki", "mount_point": "wiki", "name": "wiki"}, {"label": "Patches", "mount_point": "patches", "name": "tickets"}, {"label": "Code", "mount_point": "code", "name": "svn"}, {"label": "Activity", "mount_point": "activity", "name": "activity"}, {"label": "Mailing Lists", "mount_point": "mailman", "name": "mailman"}], "url": "http://sourceforge.net/p/tzdata/", "video_url": ""}
