{"_id": "516d822634309d2f05aab372", "categories": {"audience": [{"fullname": "Developers", "fullpath": "Intended Audience :: by End-User Class :: Developers", "id": 3, "shortname": "developers"}], "database": [], "developmentstatus": [{"fullname": "3 - Alpha", "fullpath": "Development Status :: 3 - Alpha", "id": 9, "shortname": "alpha"}], "environment": [{"fullname": "Java Swing", "fullpath": "User Interface :: Graphical :: Java Swing", "id": 471, "shortname": "ui_swing"}], "language": [{"fullname": "Java", "fullpath": "Programming Language :: Java", "id": 198, "shortname": "java"}], "license": [{"fullname": "GNU Library or Lesser General Public License version 2.0 (LGPLv2)", "fullpath": "License :: OSI-Approved Open Source :: GNU Library or Lesser General Public License version 2.0 (LGPLv2)", "id": 16, "shortname": "lgpl"}], "os": [{"fullname": "OS Independent (Written in an interpreted language)", "fullpath": "Operating System :: Grouping and Descriptive Categories :: OS Independent (Written in an interpreted language)", "id": 235, "shortname": "independent"}], "topic": [{"fullname": "User Interfaces", "fullpath": "Topic :: Software Development :: User Interfaces", "id": 561, "shortname": "softwaredev_ui"}], "translation": [{"fullname": "English", "fullpath": "Translations :: English", "id": 275, "shortname": "english"}]}, "creation_date": "2006-06-28", "developers": [{"name": "daniel", "url": "http://sourceforge.net/u/dpuryear-v/", "username": "dpuryear-v"}], "external_homepage": "http://jyatda.sourceforge.net", "icon_url": null, "labels": [], "moved_to_url": "", "name": "YetAnotherTinyDesignAssist", "preferred_support_tool": "", "preferred_support_url": "", "private": false, "screenshots": [{"caption": "BeanBagger I - Design Mode ", "thumbnail_url": "http://sourceforge.net/p/jyatda/screenshot/93219.jpg/thumb", "url": "http://sourceforge.net/p/jyatda/screenshot/93219.jpg"}], "short_description": "jYATDA is simply \"Yet Another Tiny Design Assistant\" in Java. It is a study in the patterns and techniques required for the development of a tool to assist in the layout of Java visual components on a design surface and persisting the incremental desig", "shortname": "jyatda", "socialnetworks": [], "status": "active", "summary": "", "tools": [{"label": "Files", "mount_point": "files", "name": "files"}, {"label": "Summary", "mount_point": "summary", "name": "summary", "sourceforge_group_id": 171149}, {"label": "Support", "mount_point": "support", "name": "support"}, {"label": "Reviews", "mount_point": "reviews", "name": "reviews"}, {"label": "Wiki", "mount_point": "wiki", "name": "wiki"}, {"label": "News", "mount_point": "news", "name": "blog"}, {"label": "Discussion", "mount_point": "discussion", "name": "discussion"}], "url": "http://sourceforge.net/p/jyatda/", "video_url": ""}
