{"_id": "517abd9234309d2f53566e0d", "categories": {"audience": [], "database": [], "developmentstatus": [], "environment": [], "language": [], "license": [], "os": [], "topic": [], "translation": []}, "creation_date": "2011-05-26", "developers": [{"name": "Sebastien Bernaud", "url": "http://sourceforge.net/u/fanaid/", "username": "fanaid"}, {"name": "Thomas Provoost", "url": "http://sourceforge.net/u/thomasprovoost/", "username": "thomasprovoost"}], "external_homepage": "http://existence.sourceforge.net", "icon_url": null, "labels": [], "moved_to_url": "", "name": "Existence", "preferred_support_tool": "", "preferred_support_url": "", "private": false, "screenshots": [], "short_description": "Existence Projext ESGI", "shortname": "existence", "socialnetworks": [], "status": "active", "summary": "", "tools": [{"label": "Summary", "mount_point": "summary", "name": "summary", "sourceforge_group_id": 550135}, {"label": "Support", "mount_point": "support", "name": "support"}, {"label": "Reviews", "mount_point": "reviews", "name": "reviews"}, {"label": "Files", "mount_point": "files", "name": "files"}, {"label": "Wiki", "mount_point": "wiki", "name": "wiki"}, {"label": "Code", "mount_point": "code", "name": "svn"}], "url": "http://sourceforge.net/p/existence/", "video_url": ""}
