{"status": "active", "external_homepage": "http://hook-filter.sourceforge.net", "developers": [{"url": "http://sourceforge.net/u/userid-1522774/", "username": "erwan_lemonnier", "name": "Erwan Lemonnier"}], "screenshots": [], "name": "Hook::Filter", "preferred_support_tool": "", "preferred_support_url": "", "icon_url": null, "labels": [], "video_url": "", "private": false, "creation_date": "2007-05-15", "url": "http://sourceforge.net/p/hook-filter/", "socialnetworks": [], "short_description": "Hook::Filter is a runtime firewall for subroutine calls in Perl.", "moved_to_url": "", "shortname": "hook-filter", "_id": "514b780934309d2eda5eaa69", "tools": [{"mount_point": "files", "name": "files", "label": "Files"}, {"sourceforge_group_id": 196433, "mount_point": "summary", "name": "summary", "label": "Summary"}, {"mount_point": "support", "name": "support", "label": "Support"}, {"mount_point": "reviews", "name": "reviews", "label": "Reviews"}, {"mount_point": "wiki", "name": "wiki", "label": "Wiki"}, {"mount_point": "code", "name": "cvs", "label": "Code"}], "summary": "", "categories": {"developmentstatus": [{"fullpath": "Development Status :: 5 - Production/Stable", "shortname": "production", "fullname": "5 - Production/Stable", "id": 11}], "topic": [{"fullpath": "Topic :: Software Development", "shortname": "development", "fullname": "Software Development", "id": 45}], "language": [{"fullpath": "Programming Language :: Perl", "shortname": "perl", "fullname": "Perl", "id": 176}], "license": [{"fullpath": "License :: OSI-Approved Open Source :: Artistic License", "shortname": "artistic", "fullname": "Artistic License", "id": 17}], "database": [], "environment": [], "audience": [{"fullpath": "Intended Audience :: by End-User Class :: Developers", "shortname": "developers", "fullname": "Developers", "id": 3}], "translation": [], "os": []}}
