{"_id": "513a0c4034309d546f660da0", "categories": {"audience": [], "database": [], "developmentstatus": [], "environment": [], "language": [], "license": [], "os": [], "topic": [], "translation": []}, "creation_date": "2005-05-03", "developers": [{"name": "david pitt", "url": "http://sourceforge.net/u/dpitt/", "username": "dpitt"}, {"name": "fshami", "url": "http://sourceforge.net/u/fadishami/", "username": "fadishami"}, {"name": "Greg Hester", "url": "http://sourceforge.net/u/ghester25/", "username": "ghester25"}], "external_homepage": "http://strata-tkbf.sourceforge.net", "icon_url": null, "labels": [], "moved_to_url": "", "name": "Strata TKBF", "preferred_support_tool": "", "preferred_support_url": "", "private": false, "screenshots": [], "short_description": "Strata TKBF is an enhanced version of Strata SMF. Why TKBF? Well, the enhancers initials of course -- Troy Tolle and Kyle Twogood. TKBF helps you create Strata Brokers that persist objects in relational databases.", "shortname": "strata-tkbf", "socialnetworks": [], "status": "active", "summary": "", "tools": [{"label": "Files", "mount_point": "files", "name": "files"}, {"label": "Summary", "mount_point": "summary", "name": "summary", "sourceforge_group_id": 137995}, {"label": "Support", "mount_point": "support", "name": "support"}, {"label": "Reviews", "mount_point": "reviews", "name": "reviews"}, {"label": "Wiki", "mount_point": "wiki", "name": "wiki"}, {"label": "Code", "mount_point": "code", "name": "cvs"}], "url": "http://sourceforge.net/p/strata-tkbf/", "video_url": ""}
