{"_id": "5140e818271846030f5b0920", "categories": {"audience": [{"fullname": "System Administrators", "fullpath": "Intended Audience :: by End-User Class :: System Administrators", "id": 4, "shortname": "sysadmins"}], "database": [], "developmentstatus": [{"fullname": "1 - Planning", "fullpath": "Development Status :: 1 - Planning", "id": 7, "shortname": "planning"}], "environment": [{"fullname": "Handheld/Mobile/PDA", "fullpath": "User Interface :: Graphical :: Handheld/Mobile/PDA", "id": 314, "shortname": "handhelds"}], "language": [{"fullname": "C++", "fullpath": "Programming Language :: C++", "id": 165, "shortname": "cpp"}], "license": [{"fullname": "Common Public License 1.0", "fullpath": "License :: OSI-Approved Open Source :: Common Public License 1.0", "id": 307, "shortname": "ibmcpl"}], "os": [{"fullname": "SymbianOS", "fullpath": "Operating System :: Handheld/Embedded Operating Systems :: SymbianOS", "id": 444, "shortname": "symbianos"}, {"fullname": "32-bit MS Windows (NT/2000/XP)", "fullpath": "Operating System :: Grouping and Descriptive Categories :: 32-bit MS Windows (NT/2000/XP)", "id": 219, "shortname": "winnt"}], "topic": [{"fullname": "Wireless", "fullpath": "Topic :: System :: Networking :: Wireless", "id": 566, "shortname": "wireless"}], "translation": []}, "creation_date": "2006-06-13", "developers": [{"name": "BruceX", "url": "http://sourceforge.net/u/brucexq/", "username": "brucexq"}], "external_homepage": "http://mobilesprite.sourceforge.net", "icon_url": null, "labels": [], "moved_to_url": "", "name": "MoblieSprite", "preferred_support_tool": "", "preferred_support_url": "", "private": false, "screenshots": [], "short_description": "The MobileSprite project use network extend mobliephone function and space.", "shortname": "mobilesprite", "socialnetworks": [], "status": "active", "summary": "", "tools": [{"label": "Summary", "mount_point": "summary", "name": "summary", "sourceforge_group_id": 169580}, {"label": "Support", "mount_point": "support", "name": "support"}, {"label": "Reviews", "mount_point": "reviews", "name": "reviews"}, {"label": "Wiki", "mount_point": "wiki", "name": "wiki"}, {"label": "Files", "mount_point": "files", "name": "files"}, {"label": "Mailing Lists", "mount_point": "mailman", "name": "mailman"}], "url": "http://sourceforge.net/p/mobilesprite/", "video_url": ""}
