{"_id": "514cc3b127184602a913b0f8", "categories": {"audience": [{"fullname": "Religion", "fullpath": "Intended Audience :: by Industry or Sector :: Religion", "id": 366, "shortname": "religion"}], "database": [], "developmentstatus": [{"fullname": "3 - Alpha", "fullpath": "Development Status :: 3 - Alpha", "id": 9, "shortname": "alpha"}], "environment": [], "language": [{"fullname": "C++", "fullpath": "Programming Language :: C++", "id": 165, "shortname": "cpp"}], "license": [{"fullname": "GNU General Public License version 2.0 (GPLv2)", "fullpath": "License :: OSI-Approved Open Source :: GNU General Public License version 2.0 (GPLv2)", "id": 15, "shortname": "gpl"}], "os": [{"fullname": "BeOS", "fullpath": "Operating System :: Other Operating Systems :: BeOS", "id": 224, "shortname": "beos"}], "topic": [{"fullname": "Religion and Philosophy", "fullpath": "Topic :: Religion and Philosophy", "id": 132, "shortname": "religion"}], "translation": [{"fullname": "English", "fullpath": "Translations :: English", "id": 275, "shortname": "english"}]}, "creation_date": "2004-08-11", "developers": [{"name": "Kevin Field", "url": "http://sourceforge.net/u/lackofknack/", "username": "lackofknack"}, {"name": "Paradoxianer", "url": "http://sourceforge.net/u/paradoxianer/", "username": "paradoxianer"}, {"name": "DarkWyrm", "url": "http://sourceforge.net/u/darkwyrm/", "username": "darkwyrm"}, {"name": "jan__64", "url": "http://sourceforge.net/u/userid-1103350/", "username": "jan__64"}], "external_homepage": "http://www.be-logos.org", "icon_url": null, "labels": [], "moved_to_url": "", "name": "be-logos", "preferred_support_tool": "_url", "preferred_support_url": "http://sourceforge.net/project/memberlist.php?group_id=116630", "private": false, "screenshots": [], "short_description": "Be-Logos is a Bible reader program for BeOS based on the SWORD Project API licensed under the GPL.", "shortname": "be-logos", "socialnetworks": [], "status": "active", "summary": "", "tools": [{"label": "Summary", "mount_point": "summary", "name": "summary", "sourceforge_group_id": 116630}, {"label": "Support", "mount_point": "support", "name": "support"}, {"label": "Reviews", "mount_point": "reviews", "name": "reviews"}, {"label": "Files", "mount_point": "files", "name": "files"}, {"label": "Wiki", "mount_point": "wiki", "name": "wiki"}, {"label": "Mailing Lists", "mount_point": "mailman", "name": "mailman"}, {"label": "Discussion", "mount_point": "discussion", "name": "discussion"}, {"label": "Old Repo (CVS)", "mount_point": "code", "name": "cvs"}, {"label": "Code", "mount_point": "mercurial", "name": "hg"}], "url": "http://sourceforge.net/p/be-logos/", "video_url": ""}
