{"status": "active", "preferred_support_tool": "", "preferred_support_url": "", "labels": [], "private": false, "creation_date": "2011-04-18", "socialnetworks": [], "tools": [{"sourceforge_group_id": 535261, "mount_point": "summary", "name": "summary", "label": "Summary"}, {"mount_point": "support", "name": "support", "label": "Support"}, {"mount_point": "reviews", "name": "reviews", "label": "Reviews"}, {"mount_point": "files", "name": "files", "label": "Files"}, {"mount_point": "wiki", "name": "wiki", "label": "Wiki"}, {"mount_point": "donate", "name": "link", "label": "Donate"}, {"mount_point": "code", "name": "svn", "label": "Code"}, {"mount_point": "activity", "name": "activity", "label": "Activity"}], "categories": {"developmentstatus": [{"fullpath": "Development Status :: 1 - Planning", "fullname": "1 - Planning", "shortname": "planning", "id": 7}], "environment": [{"fullpath": "User Interface :: Toolkits/Libraries :: wxWidgets", "fullname": "wxWidgets", "shortname": "ui_wxwidgets", "id": 481}], "language": [{"fullpath": "Programming Language :: Erlang", "fullname": "Erlang", "shortname": "erlang", "id": 264}], "license": [{"fullpath": "License :: OSI-Approved Open Source :: GNU General Public License version 3.0 (GPLv3)", "fullname": "GNU General Public License version 3.0 (GPLv3)", "shortname": "gplv3", "id": 679}], "database": [], "topic": [{"fullpath": "Topic :: Software Development :: Collaborative development tools", "fullname": "Collaborative development tools", "shortname": "collaborative", "id": 761}], "audience": [{"fullpath": "Intended Audience :: by End-User Class :: Developers", "fullname": "Developers", "shortname": "developers", "id": 3}], "translation": [], "os": []}, "_id": "5182c50034309d2f53a3f4a9", "name": "Uratool", "url": "http://sourceforge.net/p/uratool/", "icon_url": null, "video_url": "", "screenshots": [], "summary": "", "short_description": "The idea behind the project is to build a collaborative peer-to-peer coding editor. It will also have features like hot code loading, so you can for example rewrite the editor in itself and run the new editor without reopening it.", "moved_to_url": "", "shortname": "uratool", "developers": [{"url": "http://sourceforge.net/u/kiiii/", "username": "kiiii", "name": "Kristiina Ausmees"}, {"url": "http://sourceforge.net/u/jallajocke/", "username": "jallajocke", "name": "Joakim Lindqvist"}, {"url": "http://sourceforge.net/u/mydow/", "username": "mydow", "name": "Joakim Hansson"}, {"url": "http://sourceforge.net/u/jmr90/", "username": "jmr90", "name": "Jens Rosén"}, {"url": "http://sourceforge.net/u/telcub/", "username": "telcub", "name": "Tomas Sävström"}, {"url": "http://sourceforge.net/u/spydon/", "username": "spydon", "name": "spydon"}], "external_homepage": "http://uratool.sourceforge.net"}
