{"status": "active", "preferred_support_tool": "", "preferred_support_url": "", "labels": [], "private": false, "creation_date": "2008-06-04", "socialnetworks": [], "tools": [{"mount_point": "files", "name": "files", "label": "Files"}, {"sourceforge_group_id": 230193, "mount_point": "summary", "name": "summary", "label": "Summary"}, {"mount_point": "support", "name": "support", "label": "Support"}, {"mount_point": "reviews", "name": "reviews", "label": "Reviews"}, {"mount_point": "wiki", "name": "wiki", "label": "Wiki"}, {"mount_point": "mailman", "name": "mailman", "label": "Mailing Lists"}, {"mount_point": "feature-requests", "name": "tickets", "label": "Feature Requests"}, {"mount_point": "code", "name": "svn", "label": "Code"}], "categories": {"developmentstatus": [{"fullpath": "Development Status :: 4 - Beta", "fullname": "4 - Beta", "shortname": "beta", "id": 10}], "environment": [{"fullpath": "User Interface :: Web-based", "fullname": "Web-based", "shortname": "web", "id": 237}], "language": [{"fullpath": "Programming Language :: PHP", "fullname": "PHP", "shortname": "php", "id": 183}], "license": [{"fullpath": "License :: OSI-Approved Open Source :: GNU General Public License version 2.0 (GPLv2)", "fullname": "GNU General Public License version 2.0 (GPLv2)", "shortname": "gpl", "id": 15}], "database": [{"fullpath": "Database Environment :: Network-based DBMS :: MySQL", "fullname": "MySQL", "shortname": "db_net_mysql", "id": 524}], "topic": [{"fullpath": "Topic :: Desktop Environment :: Gnome", "fullname": "Gnome", "shortname": "gnome", "id": 58}, {"fullpath": "Topic :: Education :: Testing", "fullname": "Testing", "shortname": "testing", "id": 73}], "audience": [{"fullpath": "Intended Audience :: by End-User Class :: Advanced End Users", "fullname": "Advanced End Users", "shortname": "enduser_advanced", "id": 536}], "translation": [{"fullpath": "Translations :: Spanish", "fullname": "Spanish", "shortname": "spanish", "id": 277}], "os": [{"fullpath": "Operating System :: Modern (Vendor-Supported) Desktop Operating Systems :: Linux", "fullname": "Linux", "shortname": "linux", "id": 201}]}, "_id": "51780fa45fcbc9797b13fcb9", "name": "Valoración competencia trabajo en grupo", "url": "http://sourceforge.net/p/valoracompetgr/", "icon_url": null, "video_url": "", "screenshots": [{"url": "http://sourceforge.net/p/valoracompetgr/screenshot/196990.jpg", "caption": "Asignacin de preguntas", "thumbnail_url": "http://sourceforge.net/p/valoracompetgr/screenshot/196990.jpg/thumb"}, {"url": "http://sourceforge.net/p/valoracompetgr/screenshot/196994.jpg", "caption": "Calificaciones y valoraciones por estudiante", "thumbnail_url": "http://sourceforge.net/p/valoracompetgr/screenshot/196994.jpg/thumb"}, {"url": "http://sourceforge.net/p/valoracompetgr/screenshot/196998.jpg", "caption": "Valoracin del estudiante", "thumbnail_url": "http://sourceforge.net/p/valoracompetgr/screenshot/196998.jpg/thumb"}, {"url": "http://sourceforge.net/p/valoracompetgr/screenshot/196996.jpg", "caption": "Listado con calificacin final", "thumbnail_url": "http://sourceforge.net/p/valoracompetgr/screenshot/196996.jpg/thumb"}, {"url": "http://sourceforge.net/p/valoracompetgr/screenshot/196988.jpg", "caption": "Pantalla para la gestin de trabajos", "thumbnail_url": "http://sourceforge.net/p/valoracompetgr/screenshot/196988.jpg/thumb"}, {"url": "http://sourceforge.net/p/valoracompetgr/screenshot/196992.jpg", "caption": "Entrada de calificaciones", "thumbnail_url": "http://sourceforge.net/p/valoracompetgr/screenshot/196992.jpg/thumb"}], "summary": "", "short_description": "Esta aplicación permite que los alumnos que trabajen en grupo puedan evaluar al resto de sus compañeros.", "moved_to_url": "", "shortname": "valoracompetgr", "developers": [{"url": "http://sourceforge.net/u/josumendivil/", "username": "josumendivil", "name": "Josué Mendivil"}], "external_homepage": "http://valoracompetgr.sourceforge.net"}
