{"status": "active", "preferred_support_tool": "", "preferred_support_url": "", "labels": [], "private": false, "creation_date": "2010-10-25", "socialnetworks": [], "tools": [{"sourceforge_group_id": 366310, "mount_point": "summary", "name": "summary", "label": "Summary"}, {"mount_point": "support", "name": "support", "label": "Support"}, {"mount_point": "reviews", "name": "reviews", "label": "Reviews"}, {"mount_point": "files", "name": "files", "label": "Files"}, {"mount_point": "wiki", "name": "wiki", "label": "Wiki"}, {"mount_point": "code", "name": "svn", "label": "Code"}], "categories": {"developmentstatus": [], "environment": [], "language": [], "license": [], "database": [], "topic": [], "audience": [], "translation": [], "os": []}, "_id": "5183c0dbe88f3d77a53f0219", "name": "XS-PERU", "url": "http://sourceforge.net/p/xs-peru/", "icon_url": null, "video_url": "", "screenshots": [], "summary": "", "short_description": "Software customization for peruvian schoolserver ", "moved_to_url": "", "shortname": "xs-peru", "developers": [{"url": "http://sourceforge.net/u/aliosh2006/", "username": "aliosh2006", "name": "aliosh neira"}], "external_homepage": "http://xs-peru.sourceforge.net"}
