{"status": "active", "external_homepage": "http://drexamin8rbeta.sourceforge.net", "developers": [{"url": "http://sourceforge.net/u/crabquiche/", "username": "crabquiche", "name": "CrabQuiche"}], "screenshots": [{"url": "http://sourceforge.net/p/drexamin8rbeta/screenshot/246148.jpg", "caption": "SplashScreen", "thumbnail_url": "http://sourceforge.net/p/drexamin8rbeta/screenshot/246148.jpg/thumb"}, {"url": "http://sourceforge.net/p/drexamin8rbeta/screenshot/246150.jpg", "caption": "The Main Program", "thumbnail_url": "http://sourceforge.net/p/drexamin8rbeta/screenshot/246150.jpg/thumb"}], "name": "Dr Exam!n8r Beta - AutoHotkey", "preferred_support_tool": "", "preferred_support_url": "", "icon_url": null, "labels": [], "video_url": "", "private": false, "creation_date": "2010-01-05", "url": "http://sourceforge.net/p/drexamin8rbeta/", "socialnetworks": [], "short_description": "This is a quizzing tool.", "moved_to_url": "", "shortname": "drexamin8rbeta", "_id": "515b36c027184634944b8f85", "tools": [{"sourceforge_group_id": 297100, "mount_point": "summary", "name": "summary", "label": "Summary"}, {"mount_point": "support", "name": "support", "label": "Support"}, {"mount_point": "reviews", "name": "reviews", "label": "Reviews"}, {"mount_point": "wiki", "name": "wiki", "label": "Wiki"}, {"mount_point": "files", "name": "files", "label": "Files"}, {"mount_point": "activity", "name": "activity", "label": "Activity"}], "summary": "", "categories": {"developmentstatus": [], "topic": [], "language": [], "license": [], "database": [], "environment": [], "audience": [], "translation": [], "os": []}}
