{"_id": "5461c0163e5e83161280abdb", "categories": {"audience": [], "database": [], "developmentstatus": [], "environment": [], "language": [], "license": [{"fullname": "GNU General Public License version 2.0 (GPLv2)", "fullpath": "License :: OSI-Approved Open Source :: GNU General Public License version 2.0 (GPLv2)", "id": 15, "shortname": "gpl"}], "os": [{"fullname": "All 32-bit MS Windows (95/98/NT/2000/XP)", "fullpath": "Operating System :: Grouping and Descriptive Categories :: All 32-bit MS Windows (95/98/NT/2000/XP)", "id": 435, "shortname": "mswin_all32bit"}, {"fullname": "Windows 7", "fullpath": "Operating System :: Modern (Vendor-Supported) Desktop Operating Systems :: Windows 7", "id": 851, "shortname": "win7"}, {"fullname": "Windows 8", "fullpath": "Operating System :: Modern (Vendor-Supported) Desktop Operating Systems :: Windows 8", "id": 906, "shortname": "windows_8"}], "topic": [{"fullname": "Email", "fullpath": "Topic :: Communications :: Email", "id": 28, "shortname": "email"}, {"fullname": "Backup", "fullpath": "Topic :: System :: Storage :: Archiving :: Backup", "id": 137, "shortname": "backup"}], "translation": []}, "creation_date": "2014-11-11", "developers": [{"name": "David Saina", "url": "http://sourceforge.net/u/davidsaina/", "username": "davidsaina"}], "external_homepage": "http://yahoomailbackup.sourceforge.net", "icon_url": "http://sourceforge.net/p/yahoomailbackup/icon", "labels": ["Yahoo Mail Backup"], "moved_to_url": "", "name": "Yahoo Mail Backup", "preferred_support_tool": "_url", "preferred_support_url": "http://www.yahoo.googleapps--backup.com/", "private": false, "screenshots": [{"caption": "Yahoo Mail Backup Process", "thumbnail_url": "http://sourceforge.net/p/yahoomailbackup/screenshot/progress-status.png/thumb", "url": "http://sourceforge.net/p/yahoomailbackup/screenshot/progress-status.png"}], "short_description": "Yahoo Mail Backup is safe & reliable backup program to backup Yahoo account emails into multiple file formats as PST/EML/MBOX and MSG. Users can backup Yahoo account inbox, drafts, sent items, deleted items and trash items into any of the formats. This helps to access Yahoo account emails to local hard drive of the computer in any application that supports respective file formats like MS Outlook, Outlook Express, Windows Live Mail and Microsoft Entourage etc.", "shortname": "yahoomailbackup", "socialnetworks": [{"accounturl": "", "socialnetwork": "Twitter"}, {"accounturl": null, "socialnetwork": "Facebook"}], "status": "active", "summary": "", "tools": [{"label": "Activity", "mount_point": "activity", "name": "activity"}, {"label": "Summary", "mount_point": "summary", "name": "summary", "sourceforge_group_id": 2360774}, {"label": "Files", "mount_point": "files", "name": "files"}, {"label": "Reviews", "mount_point": "reviews", "name": "reviews"}, {"label": "Support", "mount_point": "support", "name": "support"}, {"label": "Wiki", "mount_point": "wiki", "name": "wiki"}, {"label": "Code", "mount_point": "code", "name": "git"}, {"label": "Tickets", "mount_point": "tickets", "name": "tickets"}, {"label": "Discussion", "mount_point": "discussion", "name": "discussion"}], "url": "http://sourceforge.net/p/yahoomailbackup/", "video_url": null}
