{"_id": "5335b3b73e5e8362bb87cd5b", "categories": {"audience": [], "database": [], "developmentstatus": [], "environment": [], "language": [], "license": [], "os": [], "topic": [], "translation": []}, "creation_date": "2014-03-28", "developers": [{"name": "llola", "url": "http://sourceforge.net/u/serurierantibe/", "username": "serurierantibe"}], "external_homepage": "http://serruriersantibes.fr/", "icon_url": null, "labels": [], "moved_to_url": "", "name": "serrurier antibes", "preferred_support_tool": "_url", "preferred_support_url": "http://serruriersantibes.fr/", "private": false, "screenshots": [], "short_description": "Chaque probl\u00e8me de serrurerie a sa solution, et Serrurier Antibes assure des interventions de qualit\u00e9 quelle que soit le besoin. Vous \u00eates \u00e0 Antibes, 06600, http://serruriersantibes.fr/", "shortname": "serrurierantibes", "socialnetworks": [{"accounturl": "", "socialnetwork": "Twitter"}, {"accounturl": null, "socialnetwork": "Facebook"}], "status": "active", "summary": "", "tools": [{"label": "Summary", "mount_point": "summary", "name": "summary", "sourceforge_group_id": 2170644}, {"label": "Support", "mount_point": "support", "name": "support"}, {"label": "Discussion", "mount_point": "discussion", "name": "discussion"}, {"label": "Reviews", "mount_point": "reviews", "name": "reviews"}, {"label": "Activity", "mount_point": "activity", "name": "activity"}, {"label": "Files", "mount_point": "files", "name": "files"}, {"label": "Wiki", "mount_point": "wiki", "name": "wiki"}, {"label": "Code", "mount_point": "code", "name": "git"}, {"label": "Tickets", "mount_point": "tickets", "name": "tickets"}], "url": "http://sourceforge.net/p/serrurierantibes/", "video_url": null}
