{"_id": "51507a8727184634d59ba31e", "categories": {"audience": [{"fullname": "System Administrators", "fullpath": "Intended Audience :: by End-User Class :: System Administrators", "id": 4, "shortname": "sysadmins"}], "database": [], "developmentstatus": [{"fullname": "4 - Beta", "fullpath": "Development Status :: 4 - Beta", "id": 10, "shortname": "beta"}], "environment": [{"fullname": "Non-interactive (Daemon)", "fullpath": "User Interface :: Non-interactive (Daemon)", "id": 238, "shortname": "daemon"}], "language": [{"fullname": "C++", "fullpath": "Programming Language :: C++", "id": 165, "shortname": "cpp"}], "license": [{"fullname": "GNU General Public License version 2.0 (GPLv2)", "fullpath": "License :: OSI-Approved Open Source :: GNU General Public License version 2.0 (GPLv2)", "id": 15, "shortname": "gpl"}], "os": [{"fullname": "All POSIX (Linux/BSD/UNIX-like OSes)", "fullpath": "Operating System :: Grouping and Descriptive Categories :: All POSIX (Linux/BSD/UNIX-like OSes)", "id": 200, "shortname": "posix"}], "topic": [{"fullname": "Fax", "fullpath": "Topic :: Communications :: Fax", "id": 36, "shortname": "fax"}], "translation": []}, "creation_date": "2007-08-13", "developers": [{"name": "Ralf Friedl", "url": "http://sourceforge.net/u/ralffriedl/", "username": "ralffriedl"}], "external_homepage": "http://capispfax.sourceforge.net", "icon_url": null, "labels": [], "moved_to_url": "", "name": "CAPI SPANDSP FAX", "preferred_support_tool": "", "preferred_support_url": "", "private": false, "screenshots": [], "short_description": "Fax Transfer with CAPI and spandsp", "shortname": "capispfax", "socialnetworks": [], "status": "active", "summary": "", "tools": [{"label": "Summary", "mount_point": "summary", "name": "summary", "sourceforge_group_id": 203133}, {"label": "Support", "mount_point": "support", "name": "support"}, {"label": "Reviews", "mount_point": "reviews", "name": "reviews"}, {"label": "Files", "mount_point": "files", "name": "files"}, {"label": "Wiki", "mount_point": "wiki", "name": "wiki"}, {"label": "Activity", "mount_point": "activity", "name": "activity"}], "url": "http://sourceforge.net/p/capispfax/", "video_url": ""}
