{"_id": "53d76a391be1ce28386ff764", "categories": {"audience": [], "database": [], "developmentstatus": [{"fullname": "5 - Production/Stable", "fullpath": "Development Status :: 5 - Production/Stable", "id": 11, "shortname": "production"}], "environment": [], "language": [{"fullname": "PHP", "fullpath": "Programming Language :: PHP", "id": 183, "shortname": "php"}], "license": [], "os": [], "topic": [], "translation": []}, "creation_date": "2014-07-29", "developers": [{"name": "Tassilo", "url": "http://sourceforge.net/u/tassilo-k/", "username": "tassilo-k"}], "external_homepage": "http://sourceforge.net/projects/captiveportalplus", "icon_url": null, "labels": ["pfsense", "voucher", "captive portal plus"], "moved_to_url": "", "name": "Captive Portal Plus", "preferred_support_tool": "wiki", "preferred_support_url": "", "private": false, "screenshots": [{"caption": "Voucher Tab", "thumbnail_url": "http://sourceforge.net/p/captiveportalplus/screenshot/Bildschirmfoto%202014-07-29%20um%2021.09.52.png/thumb", "url": "http://sourceforge.net/p/captiveportalplus/screenshot/Bildschirmfoto%202014-07-29%20um%2021.09.52.png"}, {"caption": "Voucher Tab", "thumbnail_url": "http://sourceforge.net/p/captiveportalplus/screenshot/Bildschirmfoto%202014-07-29%20um%2021.10.22.png/thumb", "url": "http://sourceforge.net/p/captiveportalplus/screenshot/Bildschirmfoto%202014-07-29%20um%2021.10.22.png"}, {"caption": "Generated Voucher PDF", "thumbnail_url": "http://sourceforge.net/p/captiveportalplus/screenshot/Bildschirmfoto%202014-07-29%20um%2021.12.01.png/thumb", "url": "http://sourceforge.net/p/captiveportalplus/screenshot/Bildschirmfoto%202014-07-29%20um%2021.12.01.png"}, {"caption": "Settings Tab", "thumbnail_url": "http://sourceforge.net/p/captiveportalplus/screenshot/Bildschirmfoto%202014-07-29%20um%2021.07.58.png/thumb", "url": "http://sourceforge.net/p/captiveportalplus/screenshot/Bildschirmfoto%202014-07-29%20um%2021.07.58.png"}, {"caption": "Captive Portal User Manager", "thumbnail_url": "http://sourceforge.net/p/captiveportalplus/screenshot/Bildschirmfoto%202014-07-29%20um%2021.09.05.png/thumb", "url": "http://sourceforge.net/p/captiveportalplus/screenshot/Bildschirmfoto%202014-07-29%20um%2021.09.05.png"}, {"caption": "Voucher printed with receipt printer", "thumbnail_url": "http://sourceforge.net/p/captiveportalplus/screenshot/Bildschirmfoto%202014-07-30%20um%2017.30.11.png/thumb", "url": "http://sourceforge.net/p/captiveportalplus/screenshot/Bildschirmfoto%202014-07-30%20um%2017.30.11.png"}], "short_description": "A script for pfSense Version >= 2.1.\r\nGenerate on the webGUI a pdf with vouchers or send the voucher to an network receipt printer.\r\n\r\n-->\r\nFor installation instructions, etc. see wiki:\r\nhttps://sourceforge.net/p/captiveportalplus/wiki/browse_pages/\r\n-->\r\n\r\nATTENTION:\r\nWhen you update your pfSense version you must re-install CP+!\r\nBefore you update your pfSense, download the CP+ config (CP+ Settings tab)!", "shortname": "captiveportalplus", "socialnetworks": [{"accounturl": "", "socialnetwork": "Twitter"}, {"accounturl": null, "socialnetwork": "Facebook"}], "status": "active", "summary": "An add on script for pfSense 2.", "tools": [{"label": "Activity", "mount_point": "activity", "name": "activity"}, {"label": "Summary", "mount_point": "summary", "name": "summary", "sourceforge_group_id": 2292760}, {"label": "Files", "mount_point": "files", "name": "files"}, {"label": "Reviews", "mount_point": "reviews", "name": "reviews"}, {"label": "Support", "mount_point": "support", "name": "support"}, {"label": "Help", "mount_point": "wiki", "name": "wiki"}, {"label": "Tickets", "mount_point": "tickets", "name": "tickets"}, {"label": "Discussion", "mount_point": "discussion", "name": "discussion"}, {"label": "Blog", "mount_point": "blog", "name": "blog"}], "url": "http://sourceforge.net/p/captiveportalplus/", "video_url": null}
