{"_id": "52357c0824b0d9636268b7dc", "categories": {"audience": [], "database": [], "developmentstatus": [], "environment": [], "language": [], "license": [], "os": [], "topic": [], "translation": []}, "creation_date": "2013-09-15", "developers": [{"name": "Nguyen Hua Anh", "url": "http://sourceforge.net/u/bluesky012/", "username": "bluesky012"}], "external_homepage": "http://www.phongkhamthienhoa.vn/", "icon_url": null, "labels": [], "moved_to_url": "", "name": "Ch\u1eefa b\u1ec7nh ph\u1ee5 khoa", "preferred_support_tool": "", "preferred_support_url": "", "private": false, "screenshots": [{"caption": "Ph\u00f2ng kh\u00e1m Thi\u00ean H\u00f2a", "thumbnail_url": "http://sourceforge.net/p/chuabenhphukhoa/screenshot/logo-01.png/thumb", "url": "http://sourceforge.net/p/chuabenhphukhoa/screenshot/logo-01.png"}], "short_description": "Ph\u00f2ng kh\u00e1m \u0111a khoa Thi\u00ean H\u00f2a chuy\u00ean kh\u00e1m v\u00e0 \u0111i\u1ec1u tr\u1ecb c\u00e1c b\u1ec7nh ph\u1ee5 khoa an to\u00e0n, hi\u1ec7u qu\u1ea3. V\u1edbi ph\u01b0\u01a1ng ch\u00e2m t\u1eadn t\u00e2m t\u1eadn t\u00ecnh \u1ea5m \u00e1p nh\u01b0 gia \u0111\u00ecnh, v\u1edbi \u0111\u1ed9i ng\u0169 chuy\u00ean gia d\u00f9ng t\u00e2m \u0111\u1ec3 ch\u1eefa b\u1ec7nh \u0111\u1ea3m b\u1ea3o s\u1ee9c kh\u1ecfe cho b\u1ec7nh nh\u00e2n. \u0110\u1ec3 bi\u1ebft th\u00eam th\u00f4ng tin v\u1ec1 ph\u00f2ng kh\u00e1m vui l\u00f2ng truy c\u1eadp http://www.phongkhamthienhoa.vn/", "shortname": "chuabenhphukhoa", "socialnetworks": [{"accounturl": "", "socialnetwork": "Twitter"}, {"accounturl": "https://www.facebook.com/phongkhamthienhoa.vn", "socialnetwork": "Facebook"}], "status": "active", "summary": "", "tools": [{"label": "Wiki", "mount_point": "wiki", "name": "wiki"}, {"label": "Code", "mount_point": "code", "name": "git"}, {"label": "Support", "mount_point": "support", "name": "support"}, {"label": "Files", "mount_point": "files", "name": "files"}, {"label": "Reviews", "mount_point": "reviews", "name": "reviews"}, {"label": "Summary", "mount_point": "summary", "name": "summary", "sourceforge_group_id": 1954033}, {"label": "Discussion", "mount_point": "discussion", "name": "discussion"}, {"label": "Tickets", "mount_point": "tickets", "name": "tickets"}, {"label": "Activity", "mount_point": "activity", "name": "activity"}], "url": "http://sourceforge.net/p/chuabenhphukhoa/", "video_url": ""}
