{"status": "active", "external_homepage": "http://ipcy.sourceforge.net", "developers": [{"url": "http://sourceforge.net/u/leony/", "username": "leony", "name": "Leon"}], "screenshots": [], "name": "International Photographic Community", "preferred_support_tool": "", "preferred_support_url": "", "icon_url": null, "labels": [], "video_url": "", "private": false, "creation_date": "2005-06-05", "url": "http://sourceforge.net/p/ipcy/", "socialnetworks": [], "short_description": "Our goal is to create an online photographic community that transcends cultural and language boundaries and allow residents of many different countries to demonstrate their work and share their knowledge and experience in photography.", "moved_to_url": "", "shortname": "ipcy", "_id": "5140df145fcbc94850cca454", "tools": [{"sourceforge_group_id": 140713, "mount_point": "summary", "name": "summary", "label": "Summary"}, {"mount_point": "support", "name": "support", "label": "Support"}, {"mount_point": "reviews", "name": "reviews", "label": "Reviews"}, {"mount_point": "files", "name": "files", "label": "Files"}, {"mount_point": "wiki", "name": "wiki", "label": "Wiki"}, {"mount_point": "mailman", "name": "mailman", "label": "Mailing Lists"}, {"mount_point": "news", "name": "blog", "label": "News"}, {"mount_point": "donate", "name": "link", "label": "Donate"}], "summary": "", "categories": {"developmentstatus": [{"fullpath": "Development Status :: 7 - Inactive", "shortname": "inactive", "fullname": "7 - Inactive", "id": 358}], "topic": [], "language": [{"fullpath": "Programming Language :: PHP", "shortname": "php", "fullname": "PHP", "id": 183}], "license": [], "database": [{"fullpath": "Database Environment :: Network-based DBMS :: MySQL", "shortname": "db_net_mysql", "fullname": "MySQL", "id": 524}], "environment": [{"fullpath": "User Interface :: Web-based", "shortname": "web", "fullname": "Web-based", "id": 237}], "audience": [{"fullpath": "Intended Audience :: Other Audience", "shortname": "other", "fullname": "Other Audience", "id": 5}], "translation": [], "os": []}}
