{"status": "active", "preferred_support_tool": "", "preferred_support_url": "", "labels": [], "private": false, "creation_date": "2011-11-26", "socialnetworks": [], "tools": [{"mount_point": "home", "name": "wiki", "label": "Home"}, {"mount_point": "downloads", "name": "files", "label": "Files"}, {"mount_point": "wiki", "name": "wiki", "label": "Wiki"}, {"mount_point": "discussion", "name": "discussion", "label": "Discussion"}, {"mount_point": "code", "name": "svn", "label": "Code"}, {"mount_point": "tickets", "name": "tickets", "label": "Tickets"}, {"sourceforge_group_id": 636197, "mount_point": "summary", "name": "summary", "label": "Summary"}, {"mount_point": "reviews", "name": "reviews", "label": "Reviews"}, {"mount_point": "support", "name": "support", "label": "Support"}, {"mount_point": "activity", "name": "activity", "label": "Activity"}], "categories": {"developmentstatus": [], "environment": [], "language": [{"fullpath": "Programming Language :: C#", "fullname": "C#", "shortname": "csharp", "id": 271}], "license": [{"fullpath": "License :: Public Domain", "fullname": "Public Domain", "shortname": "publicdomain", "id": 197}], "database": [], "topic": [{"fullpath": "Topic :: Games/Entertainment", "fullname": "Games/Entertainment", "shortname": "games", "id": 80}, {"fullpath": "Topic :: Software Development :: Build Tools", "fullname": "Build Tools", "shortname": "build", "id": 46}], "audience": [], "translation": [], "os": [{"fullpath": "Operating System :: Modern (Vendor-Supported) Desktop Operating Systems :: Windows 7", "fullname": "Windows 7", "shortname": "win7", "id": 851}]}, "_id": "4ed129a71be1ce72f800022c", "name": "XNB Builder", "url": "http://sourceforge.net/p/xnbbuilder/", "icon_url": null, "video_url": "", "screenshots": [{"url": "http://sourceforge.net/p/xnbbuilder/screenshot/xna%20formatter.png", "caption": "The interface for the program.", "thumbnail_url": "http://sourceforge.net/p/xnbbuilder/screenshot/xna%20formatter.png/thumb"}], "summary": "Create .xnb files for XNA games.", "short_description": "Recently updated to fix an error where content would never be compressed.  You should update to the latest version in order to fix this.\r\n\r\nNote: The full version of XNA game studio is required for conversion.  See the ReadMe for details on where to download it.\r\n\r\nCreate .xnb files for use in XNA games.  This allows for .png to .xnb and more.  \r\n\r\nFull list of supported filetypes:\r\n\r\nGraphics Files: *.bmp;*.dds;*.dib;*.hdr;*.jpg;*.pfm;*.png;*.ppm;*.tga\r\n\r\nAutodesk FBX Files: *.fbx\r\n\r\nEffects Files: *.fx\r\n\r\nSpriteFont Files: *.spritefont\r\n\r\nX Files: *.x\r\n\r\nXNA XML Files: *.xml\r\n\r\nAudio Files: *.mp3;*.wav;*.wma\r\n\r\nVideo Files: *.wmv\r\n\r\nSupport for some filetypes may be incomplete, graphics filetypes should all be fine.  If there's an issue with converting a certain filetype, please let me know!", "moved_to_url": "", "shortname": "xnbbuilder", "developers": [{"url": "http://sourceforge.net/u/sketchyplane/", "username": "sketchyplane", "name": "SketchyPlane"}], "external_homepage": ""}
